{
  "_class": "shapeGroup",
  "clippingMaskMode": 0,
  "do_objectID": "51F801E0-960C-4031-99E2-15AC72B12BF2",
  "exportOptions": {
    "_class": "exportOptions",
    "exportFormats": [
    ],
    "includedLayerIds": [
    ],
    "layerOptions": 0,
    "shouldTrim": false
  },
  "frame": {
    "_class": "rect",
    "constrainProportions": false,
    "height": 165,
    "width": 1163,
    "x": 0,
    "y": 0
  },
  "hasClickThrough": false,
  "hasClippingMask": false,
  "isFlippedHorizontal": false,
  "isFlippedVertical": false,
  "isLocked": false,
  "isVisible": true,
  "layerListExpandedType": 0,
  "layers": [
    {
      "class": "rectangle",
      "id": "55034F82-1652-41A3-AB03-4D5FA38633CE"
    }
  ],
  "name": "Tourney Banner",
  "nameIsFixed": true,
  "resizingConstraint": 63,
  "resizingType": 0,
  "rotation": 0,
  "shouldBreakMaskChain": false,
  "style": {
    "_class": "style",
    "borders": [
      {
        "_class": "border",
        "color": {
          "_class": "color",
          "alpha": 1,
          "blue": 0.592,
          "green": 0.592,
          "red": 0.592
        },
        "fillType": 0,
        "isEnabled": false,
        "position": 1,
        "thickness": 1
      }
    ],
    "endDecorationType": 0,
    "fills": [
      {
        "_class": "fill",
        "color": {
          "_class": "color",
          "alpha": 1,
          "blue": 0.847,
          "green": 0.847,
          "red": 0.847
        },
        "fillType": 4,
        "image": {
          "_class": "MSJSONFileReference",
          "_ref": "images/21b9364be03f58bd3b4e43cb7556b03931cfd6d3",
          "_ref_class": "MSImageData"
        },
        "isEnabled": true,
        "noiseIndex": 0,
        "noiseIntensity": 0,
        "patternFillType": 1,
        "patternTileScale": 1
      }
    ],
    "miterLimit": 10,
    "startDecorationType": 0
  },
  "userInfo": {
    "com.animaapp.stc-sketch-plugin": {
      "kModelPropertiesKey": {
      }
    },
    "com.invisionlabs.duplicate": {
      "photos-duplicate": {
        "asTile": 0,
        "items": [
          {
            "link": "https://media.rbl.ms/image?u=%2Ffiles%2F2016%2F04%2F11%2F635959361443851750-1434722068_pickleball-tournament.jpg&ho=https%3A%2F%2Faz616578.vo.msecnd.net&s=939&h=123de4ecac9f7358159ad5d5aac214385c64d1d2b6f68bf08b10cb0e7b5bb6c2&size=980x&c=3418239185",
            "type": "src"
          }
        ],
        "mode": "web"
      }
    }
  },
  "windingRule": 1
}